uimages/__init__.py
uimages/cli.py
uimages/main.py
uimages/processor.py
uimages-0.1.1.dist-info/LICENSE
uimages-0.1.1.dist-info/METADATA
uimages-0.1.1.dist-info/WHEEL
uimages-0.1.1.dist-info/entry_points.txt
uimages-0.1.1.dist-info/RECORD
